{"cameraMode":{"drawMode":0,"name":"Shaded","section":"Shading Mode"},"sceneLighting":true,"audioPlay":false,"sceneViewState":{"m_AlwaysRefresh":false,"showFog":true,"showSkybox":true,"showFlares":true,"showImageEffects":true,"showParticleSystems":true,"showVisualEffectGraphs":true,"m_FxEnabled":true},"in2DMode":false,"pivot":{"x":3.953704833984375,"y":58.982391357421878,"z":-165.3586883544922},"rotation":{"x":-0.2274601310491562,"y":0.694794774055481,"z":-0.2487516552209854,"w":-0.6352963447570801},"size":230.69544982910157,"orthographic":false}